lpmodes.py
lpmodes_gui.py
gui_lib/im_tools.py
gui_lib/image_display.py
lpmodes-1.0.1.dist-info/LICENSE
lpmodes-1.0.1.dist-info/METADATA
lpmodes-1.0.1.dist-info/WHEEL
lpmodes-1.0.1.dist-info/top_level.txt
lpmodes-1.0.1.dist-info/RECORD
