Metadata-Version: 2.1
Name: lpmodes
Version: 1.0.1
Summary: Solve modes for a step index multimode fibre and simulate beam coupling and propagation.
Author-email: Michael Hughes <m.r.hughes@kent.ac.uk>
License: MIT License
Project-URL: Homepage, https://github.com/MikeHughesKent/lpmodes/
Keywords: fibre,fiber,modes,lp modes,multimode,simulation
Classifier: License :: OSI Approved :: MIT License
Classifier: Programming Language :: Python
Classifier: Programming Language :: Python :: 3
Requires-Python: >=3.8
License-File: LICENSE
Requires-Dist: matplotlib>=3.3.4
Requires-Dist: numpy>=1.22
Requires-Dist: Pillow>=9
Requires-Dist: scipy>=1.7
Requires-Dist: pyqt5>5.0.0
